pykalimux/__init__.py
pykalimux/pykalimux.py
pykalimux-1.5.dist-info/licenses/LICENSE
pykalimux-1.5.dist-info/METADATA
pykalimux-1.5.dist-info/WHEEL
pykalimux-1.5.dist-info/entry_points.txt
pykalimux-1.5.dist-info/top_level.txt
pykalimux-1.5.dist-info/RECORD
