Metadata-Version: 2.4
Name: pykalimux
Version: 1.5
Summary: This is a python script by which you can install Kali Nethunter (Kali Linux) in your termux application without rooted phone.
Home-page: https://github.com/rc-chuah/pykalimux
Author: RC Chuah
Author-email: raynersec@gmail.com
License: GNU General Public License v3 (GPLv3)
Project-URL: Source, https://github.com/RaynerSec/pykalimux
Keywords: kali,kalilinux,kalinethunter,infosec,cybersec,infosecurity,cybersecurity
Classifier: Development Status :: 5 - Production/Stable
Classifier: Environment :: Console
Classifier: Intended Audience :: Developers
Classifier: Intended Audience :: Information Technology
Classifier: Intended Audience :: System Administrators
Classifier: License :: OSI Approved :: GNU General Public License v3 (GPLv3)
Classifier: Natural Language :: English
Classifier: Programming Language :: Python
Classifier: Programming Language :: Python :: 2
Classifier: Programming Language :: Python :: 3
Classifier: Operating System :: Android
Classifier: Topic :: Security
Classifier: Topic :: Utilities
License-File: LICENSE
Dynamic: author
Dynamic: author-email
Dynamic: classifier
Dynamic: description
Dynamic: description-content-type
Dynamic: home-page
Dynamic: keywords
Dynamic: license
Dynamic: license-file
Dynamic: project-url
Dynamic: summary
